jt_ops/__init__.py
jt_ops-0.0.1.dist-info/LICENCE
jt_ops-0.0.1.dist-info/METADATA
jt_ops-0.0.1.dist-info/WHEEL
jt_ops-0.0.1.dist-info/top_level.txt
jt_ops-0.0.1.dist-info/RECORD
