Metadata-Version: 2.1
Name: jt-ops
Version: 0.0.1
Summary: Python Package for usefull global functions
Home-page: https://linkedin.com/in/joetilsed/
Author: Joe Tilsed
Author-email: Joe@Tilsed.com
License: UNKNOWN
Keywords: jt_ops python
Platform: UNKNOWN
Classifier: Programming Language :: Python :: 3
Classifier: License :: OSI Approved :: MIT License
Classifier: Operating System :: OS Independent
